{
  "ddqn_beamrider": {
    "agent": [{
      "name": "DoubleDQN",
      "algorithm": {
        "name": "DoubleDQN",
        "action_pdtype": "Argmax",
        "action_policy": "epsilon_greedy",
        "explore_var_spec": {
          "name": "linear_decay",
          "start_val": 1.0,
          "end_val": 0.01,
          "start_step": 10000,
          "end_step": 1000000
        },
        "gamma": 0.99,
        "training_batch_epoch": 1,
        "training_epoch": 1,
        "training_frequency": 4,
        "training_start_step": 10000,
        "normalize_state": false
      },
      "memory": {
        "name": "AtariReplay",
        "batch_size": 32,
        "max_size": 200000,
        "stack_len": 4,
        "use_cer": false,
        "alpha": 0.6,
        "epsilon": 1e-6,

      },
      "net": {
        "type": "ConvNet",
        "conv_hid_layers": [
          [32, 8, 4, 0, 1],
          [64, 4, 2, 0, 1],
          [64, 3, 1, 0, 1]
        ],
        "fc_hid_layers": [256],
        "hid_layers_activation": "relu",
        "init_fn": null,
        "batch_norm": false,
        "clip_grad_val": 1.0,
        "loss_spec": {
          "name": "SmoothL1Loss"
        },
        "optim_spec": {
          "name": "RMSprop",
          "lr": 2.5e-4,
          "alpha": 0.95,
          "eps": 1e-1,
          "momentum": 0.95
        },
        "lr_scheduler_spec": null,
        "update_type": "polyak",
        "update_frequency": 10,
        "polyak_coef": 0.992,
        "gpu": true
      }
    }],
    "env": [{
      "name": "BeamRiderNoFrameskip-v4",
      "max_t": null,
      "max_tick": 10000000
    }],
    "body": {
      "product": "outer",
      "num": 1
    },
    "meta": {
      "distributed": false,
      "eval_frequency": 10000,
      "max_tick_unit": "total_t",
      "max_session": 4,
      "max_trial": 12,
      "search": "RandomSearch",
      "resources": {
        "num_cpus": 12
      }
    }
  }
}
